[{"id":"9ab263e9-e1b6-4141-a08c-cffef8337b74","name":"Крем от варикоза Sumifun для ног","description":"Сумифун уход за кожей эффективное варикозное вариковое лечение Товар с Taobao. Продавец:","price":458.90}, 
 {"id":"caa64b12-72e6-406e-b8fb-0645c53aa1b0","name":"Дневной крем для лица веганский увлажняющий","description":"7 ленивых веганских дневных кремов Увлажняющие увлажнение крема для лица и Товар с Taobao. Продавец:","price":622.70}, 
 {"id":"dca15d4b-dce8-43bc-82e0-355c3a77a3d9","name":"Мгновенное объемное увлажняющее увлажнение губ","description":"Мгновенное объемное увлажняющее увлажнение губ Товар с Taobao. Продавец:","price":243.10}, 
 {"id":"e2314215-a9ce-4e65-9d06-1e1b0839d32e","name":"Коллагеновые кремы для мужчин против морщин старение лица","description":"Коллагеновые кремы для мужчин против морщин старение лица крем f Товар с Taobao. Продавец:","price":218.40}, 
 {"id":"d8cbe304-9651-48bd-b249-61a1f3c3da5c","name":"Приравнивайте плавные ванильные белковые добавки сыворотк","description":"Качественный товар из категории Здоровье и красота","price":7537.40}, 
 {"id":"e1fdbcac-5602-4a2c-a924-144df6aae501","name":"Салициловая кислота лицо сывороточная поры увлажняет бель","description":"Салициловая кислота лицо сывороточная поры увлажняет бельенин Товар с Taobao. Продавец:","price":419.90}, 
 {"id":"e3e68a29-6225-4164-96a0-d2813e70a8ea","name":"Губная помада матовая водостойкая красно-коричневая","description":"Губная помада красная коричневая помада Waterprof Увлажняющее зеркало Товар с Taobao. Продавец: healthylive","price":180.70}, 
 {"id":"81e30e08-cded-4467-ab10-c7a15dba8b4b","name":"Антивозрастной увлажняющий крем для лица дневной","description":"Collagen Cream -Anti Старение лица увлажняющий крем -день и Товар с Taobao. Продавец:","price":7664.80}, 
 {"id":"3b3fc306-6f16-4e1b-95f5-36f6306daa93","name":"Увлажняющий лосьон мужской","description":"Качественный товар из категории Здоровье и красота","price":917.80}, 
 {"id":"5f960f09-fb9f-4a3f-924f-e3a88a251358","name":"Маска-плёнка для лица глубоко очищающая","description":"Снимите маску маски для лица, блестящая маска глубоко увлажняет увлажнение Товар с Taobao. Продавец:","price":442.00}, 
 {"id":"17ecf069-703c-4c06-b373-f0c9e0c01b22","name":"Маска для лица против морщин, 5 шт","description":"Качественный товар из категории Здоровье и красота","price":9571.90}, 
 {"id":"f901cf1e-782c-4ae8-88ab-5b9b01614dd2","name":"Солнцезащитный крем Neutrogena SPF60 увлажняющий 88мл","description":"Качественный товар из категории Здоровье и красота","price":2567.50}, 
 {"id":"b713c677-c957-4a45-ba5a-5889d138f9f6","name":"Бесплатный солнцезащитный лосьон","description":"Качественный товар из категории Здоровье и красота","price":683.80}, 
 {"id":"f08590bb-60a5-4e62-973a-fba508689e25","name":"Маска-бандаж для подтяжки овала лица и подбородка V-Line","description":"Корректирующая маска-бандаж для лица с лифтинг-эффектом. Помогает подтянуть овал лица, уменьшить второй подбородок и создать чёткий V-образный контур. Эластичный материал мягко поддерживает кожу, не вызывая дискомфорта.\n\n• Назначение: коррекция овала лица, уменьшение второго подбородка\n• Эффект: V-Line (V-образный контур)\n• Материал: эластичная дышащая ткань\n• Застёжка: регулируемая на липучке\n• Применение: носить 1-2 часа в день\n• Универсальный размер\n\nРекомендуется использовать в сочетании с массажем и уходовой косметикой для максимального эффекта.","price":551.20}, 
 {"id":"0e564125-069d-47f1-acee-c8856825011b","name":"Крем для лица с ретинолом против морщин антивозрастной","description":"Качественный товар из категории Здоровье и красота","price":731.90}, 
 {"id":"3bfea848-3227-47b5-84b0-e4d9e96ef789","name":"Осветление кожи, отбеливание и увлажняющий крем для лица","description":"Осветление кожи, отбеливание и увлажняющий крем для лица Товар с Taobao. Продавец: healthylive","price":561.60}, 
 {"id":"f724662a-a96b-4842-8705-2975ff58c8ac","name":"Крем для лица с ретинолом антивозрастной","description":"Качественный товар из категории Здоровье и красота","price":6877.00}, 
 {"id":"a8a79be5-6773-4b7d-846c-c9f5fd1a2906","name":"Лицо сыворотка пополнить увлажняет термоусадочную пор","description":"Лицо сыворотка пополнить увлажняет термоусадочную пор Товар с Taobao. Продавец:","price":367.90}, 
 {"id":"8f1eb965-5b0a-40c6-8884-4b1e921d9151","name":"100% минерал SPF 50 |","description":"Cerave 100% минерал SPF 50 | Товар с Taobao. Продавец: 999","price":9480.90}, 
 {"id":"edd143cf-0c5b-4f63-bec9-c5413ae8f037","name":"Темные пятна удаляют лицо кремовое отбеливание кожи увлаж","description":"Темные пятна удаляют лицо кремовое кремовое отбеливание кожи увлажняние Товар с Taobao. Продавец:","price":410.80}, 
 {"id":"82b714af-ef01-4a5f-a829-1ae9e37c61d7","name":"Гель алоэ вера 92% увлажняющий от прыщей","description":"Bioaqua 92%алоэ вера Гель гель крема -крема для увлажняющих прыщей крем Товар с Taobao. Продавец:","price":163.80}, 
 {"id":"9f6295cb-2808-4dad-858d-ee616682f019","name":"Комплект по уходу за кожей увлажняющий глазное маска солн","description":"Комплект по уходу за кожей увлажняющий глазное маска солнцезащитный крем чистка лица Товар с Taobao. Продавец:","price":110.50}, 
 {"id":"4252dccf-7bbd-455a-8581-885c40179fd7","name":"Скраб для губ отшелушивающий уход","description":"Удалить мертвую кожу отшелушивающую скраб для ухода за губами Товар с Taobao. Продавец:","price":293.80}, 
 {"id":"12e77877-f4d6-4671-b236-1dd32fdc3e9b","name":"Уход за кожей маска для лица красота Увлажняющая листовая","description":"Уход за кожей маска для лица красота Увлажняющая листовая маска для лица Товар с Taobao. Продавец:","price":144.30}, 
 {"id":"353c505a-46d0-4cf9-9223-08f16528b038","name":"Американские подлинные Graatiae обновляя увлажняющие кремы","description":"Американские подлинные Graatiae обновляя увлажняющие кремы Товар с Taobao. Продавец:","price":8985.60}, 
 {"id":"8848aa76-1142-4875-88aa-1f47e8e39961","name":"Солнцезащитный крем-стик отбеливающий SPF50","description":"Suncreen Cream Islation Солнцезащитный кремовой палочка отбеливание MOIS Товар с Taobao. Продавец:","price":458.90}, 
 {"id":"a27235fe-89b1-4e46-86bc-aef85cf44079","name":"Отбеливающее кремовое лицо крем","description":"Minch отбеливающее кремовое лицо крем Товар с Taobao. Продавец:","price":287.30}, 
 {"id":"dc10292c-981d-44fb-9174-c3d579ddb53c","name":"Гиалуроновая кислота лицо в сыворот","description":"Гиалуроновая кислота лицо в сыворот Товар с Taobao. Продавец: DM","price":328.90}, 
 {"id":"f9b506b3-3bc6-4d13-b952-1d1449141d84","name":"Солнцезащитный крем SPF50 с защитой от ультрафиолета","description":"Солнцезащитный крем Creamspf50 Солнцезащитный крем для ультрафиолетовой защиты лица солнце Товар с Taobao. Продавец:","price":413.40}, 
 {"id":"2b48948f-ea7a-468f-b99a-cd18a50214a0","name":"Солнцезащитный крем с рисом и пробиотиками SPF50, 50мл","description":"50 мл рисового пробиотического солнцезащитного крема Органический водонепроницаемый солнцезащитный крем L Товар с Taobao. Продавец: healthylive","price":544.70}, 
 {"id":"a5781b8b-aff2-4fa3-b787-75a1b8afddbe","name":"Сыворотка для лица антивозрастная с гиалуроновой кислотой","description":"Astaxanthin Ampoule Antistering Face Сывороточная антивозрастная морщина Товар с Taobao. Продавец: healthylive","price":1115.40}, 
 {"id":"90f5621a-bec7-4982-844a-690d9a7408b5","name":"Маска для лица растительная натуральная, 8 шт","description":"8 шт. Натуральное растение маска красота по уходу за кожей маски увлажняет Товар с Taobao. Продавец:","price":339.30}, 
 {"id":"fba2cc97-7e2e-44e2-9cde-e58dc6e1c072","name":"Увлажняющий крем для лица корейская косметика","description":"Корейская косметическая красота Увлажняющая кожа Товар с Taobao. Продавец:","price":2028.00}, 
 {"id":"0a7c204a-8013-4822-854c-0f9980cccbed","name":"Сыворотка для лица с лактобионовой кислотой сужающая поры","description":"Лактобионовая кислота сыворотка сжимает поры Увлажняющая сущность Liq Товар с Taobao. Продавец: healthylive","price":379.60}, 
 {"id":"59f0de9d-ddd7-40b4-9568-cdec0a05cea9","name":"100% минеральный солнцезащитный крем SPF 50 |","description":"Cerave 100% минеральный солнцезащитный крем SPF 50 | Товар с Taobao. Продавец:","price":8031.40}, 
 {"id":"b8fc7c04-c8f2-4ae9-9599-1ff5b80f7cf3","name":"Маска велосипедная дышащая для лица","description":"Езда на велосипеде на лицевой маски для воздухопроницаемого солнечного экрана ледяной красный красный цвет Товар с Taobao. Продавец:","price":36251.80}, 
 {"id":"d28c6cc0-1f67-4691-8ffb-8adcb1e2ead3","name":"Сыворотка для лица с витамином С и ретинолом, укрепляющая","description":"Сыворотка для лица с витамином С и ретинолом, укрепляющая восстанавливающая сыворотка Товар с Taobao. Продавец: DM","price":456.30}, 
 {"id":"32974508-c028-4b3a-8ffd-6a228652879b","name":"Тонер для лица эссенция роза Гиалуроновая кислота Увлажня","description":"Тонер для лица эссенция роза Гиалуроновая кислота Увлажняющая ширина Товар с Taobao. Продавец:","price":344.50}, 
 {"id":"fa2d6ba6-db7e-4a60-a4fe-13b44abc06ac","name":"Крем от растяжек для лица восстанавливающий","description":"Прысные растягивающие марки для ремонта крема для ремонта крема для ремонта лица Товар с Taobao. Продавец: Africa","price":456.30}, 
 {"id":"f17cffc4-a65b-4020-b90d-92d2a2ad8594","name":"Сыворотка для лица в ампулах с гиалуроновой кислотой 28 шт","description":"28 бутылок/набор фуллерена гиалуроновой кислоты Ампула Сыворотка Товар с Taobao. Продавец:","price":709.80}, 
 {"id":"7608d72c-6561-4a65-bb28-f20f2bd21b12","name":"Солнцезащитный крем Spf50, изолирующий увлажняющий","description":"Солнцезащитный крем Spf50, изолирующий солнцезащитный крем, увлажняющий Товар с Taobao. Продавец:","price":109.20}, 
 {"id":"f4a9706c-5301-434b-b231-5195d386a0b1","name":"Глубокий коллаген против морщин","description":"Качественный товар из категории Здоровье и красота","price":1203.80}, 
 {"id":"6dad8ad5-5a75-4711-8a8b-4468cf381990","name":"Набор для ухода за кожей корейский увлажняющий","description":"Корейский уход за кожей установил сердечный увлажняющий тонер\n\nТовар с Taobao. Продавец: BeautyNail Art Store","price":716.30}, 
 {"id":"7d61134b-5185-4f94-bd0f-c4aff08a953d","name":"Лицевая кремовая отбеливание увлажняющие 24-километровые","description":"Лицевая кремовая отбеливание увлажняющие 24 -километровые дневные кремы\n\nТовар с Taobao. Продавец: BKXRH","price":679.90}, 
 {"id":"c97f7f52-10ab-41d7-bd5e-f9ceabdb4d04","name":"Увлажняющий крем-кол-коллаген с увлажняющим средствами","description":"Увлажняющий крем -кол -коллаген с увлажняющим средствами для увлажнения для улаты Товар с Taobao. Продавец:","price":825.50}, 
 {"id":"776e918b-e9dc-4c3e-8d00-0191faef4979","name":"Декор для ванной комнаты, стеклянное зеркало, солнцезащит","description":"Декор для ванной комнаты, стеклянное зеркало, солнцезащитные очки, европейский стиль Товар с Taobao. Продавец:","price":165.03}, 
 {"id":"038a24bf-aced-405f-a1db-9c2c9c36753c","name":"Спрей для ухода за кожей Деликатная кожа местного примене","description":"Спрей для ухода за кожей Деликатная кожа Спрей для местного применения для всего тела Нежный Товар с Taobao. Продавец:","price":312.00}, 
 {"id":"80a24a14-22f4-49b3-a25d-8db742865bac","name":"Очищающая маска для лица с экстрактом зелёного чая","description":"Чистая маска для лица красотка кожа зеленый чай чистый маска для лица Товар с Taobao. Продавец:","price":473.20}, 
 {"id":"c1facee3-aab2-415e-ac44-fc2fd58db2ec","name":"Силиконовый уход за кожей по уходу за","description":"Силиконовый уход за кожей по уходу за кожей. Товар с Taobao. Продавец:","price":421.20}, 
 {"id":"085a01ec-c28a-4ff4-8276-e2f2c7826cc8","name":"Кабельный трекер тестер RJ для поиска проводки","description":"Кабельный трекер проволоки Тропичный тонер Toner Telephone Ethernet\n\nТовар с Taobao. Продавец: JP41 Flagship Store","price":1764.10}, 
 {"id":"6722b987-e6d5-43f2-a808-28f73f52e32c","name":"Помада рука крем-духи увлажняющие растения","description":"Помада рука крем -духи увлажняющие увлажняющие растения\n\nТовар с Taobao. Продавец: tb_19670905","price":11999.00}, 
 {"id":"097ea55e-8605-4410-9be9-92d658c1d4ee","name":"Сыворотка для лица с гиалуроновой кислотой, ниацинамидом и витаминами","description":"Лицевая сыворотка гиалуроновая кислота ниацинамидная витаминная лицо кожа c Товар с Taobao. Продавец: healthylive","price":36673.00}, 
 {"id":"8ad7ce7b-6431-466f-b73f-f263f08ff8e7","name":"Ночной крем для лица осветляющий против пигментных пятен","description":"Ночной крем осветляет пятна на лице и увлажняет упругость. Товар с Taobao. Продавец:","price":404.30}, 
 {"id":"9eff6fb2-71f8-4084-843e-b453337dcd05","name":"Набор средств по уходу за кожей с коллагеном, очищающий,","description":"Набор средств по уходу за кожей с коллагеном, очищающий, омолаживающий, для лица\n\nТовар с Taobao. Продавец: Overall Makeup Store","price":297.70}, 
 {"id":"f98ee2c3-a48e-4105-8f0c-6db03067e4d1","name":"Сыворотка для лица с витамином С и ретинолом осветляющая","description":"Качественный товар из категории Здоровье и красота","price":716.30}, 
 {"id":"76f4a376-17f5-4995-b33e-9880a425caf2","name":"Гликолевая кислота алоэ вера лицом в сыворотке увлажнения","description":"Гликолевая кислота алоэ вера лицом в сыворотке увлажнения снижает прыщи Товар с Taobao. Продавец: DM","price":458.90}, 
 {"id":"9525b617-a91d-4df2-bab7-9e43488ef951","name":"Удаление от прыщей крем для восстановления кожи","description":"Удаление от прыщей крем для восстановления кожи Товар с Taobao. Продавец: Africa","price":419.90}, 
 {"id":"5c9112de-e643-4f94-a7d3-284915c3c25e","name":"Сыворотка для лица с витамином C осветляющая","description":"Новый витамин С отбеливающее лицо сыворотка радость симпатичная кислота Товар с Taobao. Продавец:","price":587.60}, 
 {"id":"5d9c5131-83e8-463b-b4e6-1f0ba0849995","name":"Отбеливающий крем для лица с коллагеном и молоком","description":"Коллагеновое молоко отбеливание лица кремового кремового крема для тела\n\nТовар с Taobao. Продавец: BeautyNail Art Store","price":275.60}, 
 {"id":"34269307-92e2-4113-b6ff-c5e4a365848d","name":"Крем для лица витаминный Удалите темные пятна отбеливающи","description":"Крем для лица витаминный крем Удалите темные пятна отбеливающие лицо Товар с Taobao. Продавец:","price":494.00}, 
 {"id":"0baf44a1-91a7-4caf-8942-18d09fdeb97d","name":"Крем для лица от прыщей восстанавливающий и осветляющий","description":"Крем для удаления от прыщей крем для восстановления кожи отбеливание крем30 г Товар с Taobao. Продавец:","price":807.30}, 
 {"id":"bf94b431-64b6-45eb-aa9a-3c0c41ca7cec","name":"Ледяной валик-кубик для ухода за лицом","description":"Ледяной валик для лица, мороженое, кубик, плесень, уход за кожей Beaut Товар с Taobao. Продавец:","price":479.70}, 
 {"id":"93b479ab-5764-4c13-a43e-c65e0323950c","name":"Оригинальная ремонтная эссенция тонера лица крема","description":"Оригинальная ремонтная эссенция тонера лица крема Товар с Taobao. Продавец:","price":639.60}, 
 {"id":"c802d50c-2296-4ad2-a25d-59cf566aad51","name":"100 г коллагена ручной работы мыла чистка лица крем","description":"100 г коллагена ручной работы мыла чистка лица крем крем Товар с Taobao. Продавец: 7172","price":478.40}, 
 {"id":"09f3d8ec-2887-45b9-a28b-8f3c1f2ac122","name":"Сыворотка для лица 77% комплексный уход за кожей","description":"Heartleaf 77% уход за кожей уход за кожей сыворот Товар с Taobao. Продавец:","price":715.00}, 
 {"id":"a787ab82-a3fd-43df-9156-437482448f77","name":"Крем для снятия волос на лице удаления 1,75","description":"Крем для снятия волос на лице Крем для удаления волос крем для волос крем 1,75 Товар с Taobao. Продавец: 7172","price":731.90}, 
 {"id":"15606514-355a-433b-be78-d224436349f2","name":"Уход за кожей Мадагаскарская центелла Поремизирующая быст","description":"Skin1004 Уход за кожей Мадагаскарская центелла Поремизирующая быстрая глина\n\nТовар с Taobao. Продавец: Overall Makeup Store","price":692.90}, 
 {"id":"8b99dff4-d09d-4110-a68a-f1155f39fba9","name":"Оригинальный корейский уход за кожей Rice Pro Biotics Sun","description":"Оригинальный корейский уход за кожей Rice Pro Biotics Sunscreen\n\nТовар с Taobao. Продавец: BeautyNail Art Store","price":709.80}, 
 {"id":"d849c05b-e71e-4152-a6d3-fc30745afa3d","name":"Сыворотка коллагеновая для лица с гиалуроновой кислотой","description":"Коллаген для ухода за кожей на лице Нико Тина Ми Хи Ялу Рон IC кислота Товар с Taobao. Продавец: healthylive","price":422.50}, 
 {"id":"6ccd5ee3-11a1-4319-b521-0348e02a191c","name":"Motions волосы и увлажняющие парикмахерские по коже головы","description":"Vadesity Motions волосы и увлажняющие парикмахерские по коже головы\n\nТовар с Taobao. Продавец: xiaobo8365","price":696.80}, 
 {"id":"6f872062-10d9-4312-afbc-fb1fee8ba784","name":"Набор ухода за кожей витамина С, очищение увлажнения","description":"Набор ухода за кожей витамина С, очищение увлажнения увлажнения Товар с Taobao. Продавец:","price":293.80}, 
 {"id":"e475cbe4-88a4-4d50-97fd-1563c9c70e0b","name":"Самостоятельная рана заправка по уходу за кожей стерильны","description":"Самостоятельная рана заправка по уходу за кожей стерильный воздух Товар с Taobao. Продавец:","price":1222.00}, 
 {"id":"19b61a6d-482b-40a2-bb05-3c39ea209cb7","name":"Куркура уход за кожей лосьон","description":"Куркура уход за кожей лосьон\n\nТовар с Taobao. Продавец: Overall Makeup Store","price":395.20}, 
 {"id":"7968e59f-a624-4cd2-98e9-3bb9927b4b19","name":"Ледяной лицевой ролик по уходу за кожей","description":"Ледяной лицевой ролик по уходу за кожей Товар с Taobao. Продавец:","price":92.30}, 
 {"id":"bcc45429-a627-4eae-a86a-965f0ad7460d","name":"Набор для ухода за кожей с экстрактом риса","description":"Распродукт ухода за рисовой кожей набор рисовых пюре из шести частей коробки Товар с Taobao. Продавец:","price":197.60}, 
 {"id":"418a829e-d50b-47d6-ba24-e1dbdb7103a3","name":"Маска-плёнка для лица от чёрных точек","description":"Черные головы лица Удалите r ream с черных точек маски по уходу за кожей по уходу за кожей по уходу за кожей по уходу за кожей Товар с Taobao. Продавец:","price":863.20}, 
 {"id":"79c75e74-a4fc-4e2e-adc2-b5de872f1c4b","name":"Набор ухода за кожей эфтефкляр ниацинамид ретинол сыворот","description":"Набор ухода за кожей эфтефкляр ниацинамид ретинол сывороточный цикапласт c Товар с Taobao. Продавец: healthylive","price":659.10}, 
 {"id":"d96d2b5a-b1aa-4336-a695-67f48b1d43ba","name":"Наборы по уходу за кожей витамина C","description":"Наборы по уходу за кожей витамина C\n\nТовар с Taobao. Продавец: Overall Makeup Store","price":393.90}, 
 {"id":"9db2e213-210e-49ca-99b7-528e96214b46","name":"Лицевой крем для лицевого крема кремовый отбеливание 1+1Pics","description":"Лицевой крем для лицевого крема кремовый кремовый отбеливание 1+1Pics Товар с Taobao. Продавец:","price":1064.70}, 
 {"id":"0dd4553f-f996-4d5d-a31d-164cf5f1686a","name":"Мать грунтовая постбиотическая увлажняющая среда сыворотка","description":"Мать грунтовая постбиотическая увлажняющая среда увлажняющая сыворотка\n\nТовар с Taobao. Продавец: xinxinxiangyin14","price":7114.90}, 
 {"id":"d0fb8afd-b51b-4781-858a-3c2829c9626c","name":"Ниацинамид увлажняющий крем для глаз анти морщин","description":"Ниацинамид увлажняющий крем для глаз Увлажняющий анти морщин Товар с Taobao. Продавец: healthylive","price":234.00}, 
 {"id":"e4e1ca47-8a11-4108-a6ad-585b1c6e9369","name":"Ретинол гиалуроновая кислота увлажняет, укрепляет","description":"Ретинол гиалуроновая кислота увлажняет, увлажняет, укрепляет Товар с Taobao. Продавец:","price":718.90}, 
 {"id":"b43e4977-b4f4-4b42-ba3f-aa5eab50af6d","name":"Крем увлажняющий с конским жиром","description":"Лошадь крем увлажняет и увлажняет крем\n\nТовар с Taobao. Продавец: tb_19670905","price":458.90}, 
 {"id":"692b11aa-f13c-471c-9a61-ed2b98731da3","name":"B5 набор на лице C10 Увлажняет и N10","description":"Essence B5 Set на лице C10 Увлажняет и увлажняет N10 Товар с Taobao. Продавец:","price":458.90}, 
 {"id":"13ac8bc8-49d3-4b23-8130-339605835d7a","name":"Бальзам для губ увлажняющий, набор 4 шт","description":"4pcs Увлажняющий бальзам для губ.\n\nТовар с Taobao. Продавец: JP41 Flagship Store","price":253.50}, 
 {"id":"8f3d4c3b-b65d-4466-b32f-f59cb74345fb","name":"Влагостойкий агент плесень","description":"Влагостойкий агент плесень Товар с Taobao. Продавец:","price":252.20}, 
 {"id":"1a82b5dd-5104-4f1c-8d2e-dbf699651870","name":"Купить один Получите два витамина С 20% крем для лица 30","description":"Купить один Получите два витамина С 20% крем для лица 30 мл крем для лиц по уходу за кожей по уходу за кожей.\n\nТовар с Taobao. Продавец: tb_19670905","price":696.80}, 
 {"id":"0fe5d563-7f81-48dd-b062-1d91726b1b8b","name":"Сыворотка для лица с гиалуроновой кислотой увлажняющая","description":"Гиалуроновая кислота лицо сывороточная лицевая сторона против старения раствор Товар с Taobao. Продавец:","price":898.30}, 
 {"id":"da1fa2f1-b297-49f6-a8b4-7078c361a733","name":"Порошок консилера увлажняет настройку и тепловой стрельбу","description":"Порошок консилера увлажняет настройку и тепловой стрельбу метода\n\nТовар с Taobao. Продавец: tb_19670905","price":221.00}, 
 {"id":"230cd208-a935-4c52-b302-bfa4eb964b61","name":"Сыворотка для лица с 24K золотом","description":"24K золотая лицевая лицевая сыворот\n\nТовар с Taobao. Продавец: BKXRH","price":716.30}, 
 {"id":"3279f41d-9afb-424c-9739-a03e6ab1c7cc","name":"Ретринол для снятия с удалением морщин в сыворотке подъем","description":"Ретринол для снятия с удалением морщин в сыворотке для подъема лиц.\n\nТовар с Taobao. Продавец: Overall Makeup Store","price":436.80}, 
 {"id":"6366f5d2-e5ce-4082-adbd-3ad6b1dcf7f6","name":"Сыворотка для лица с витамином C осветляющая антивозрастная","description":"Осветляющая сыворотка для лица с высокой концентрацией витамина C. Выравнивает тон кожи, уменьшает пигментные пятна, стимулирует выработку коллагена. Антиоксидантная защита от преждевременного старения.\n\n• Активный компонент: витамин C (15-20%)\n• Действие: осветление, anti-age, антиоксидант\n• Объём: 30 мл\n• Тип кожи: для всех типов\n• Применение: утром под крем/SPF\n• Без парабенов и силиконов","price":4585.10}, 
 {"id":"6b52b652-14bf-43b2-8556-f0e113f0d732","name":"Сыворотка ретинола против морщин","description":"Сыворотка ретинола сыворотка против морщин Товар с Taobao. Продавец:","price":513.50}, 
 {"id":"0ce23066-964a-4a66-ba62-9bc8f5e31c02","name":"Сыворотка для лица с коллагеном и экстрактом улитки антивозрастная","description":"Лицо сывороточная коллагеновая улитка эссенция против возраста отбеливание прыщей Товар с Taobao. Продавец: DM","price":366.60}, 
 {"id":"2b39c86b-3f6f-4d87-b7b5-bf262d9bcf59","name":"Стирающая сыворотка, укрепляющая твердая, влажная цветная","description":"Стирающая сыворотка, укрепляющая сыворотка, твердая, влажная цветная и гидратная поверхность URI\n\nТовар с Taobao. Продавец: Bean buns","price":386.10}, 
 {"id":"a2e8d0f7-f7b0-4826-8e78-d93a754263a7","name":"Ретинол лицевой сыворот","description":"Ретинол лицевой сыворот Товар с Taobao. Продавец: DM","price":438.10}, 
 {"id":"098521b9-3264-42f0-b1e0-4a87e77f5d19","name":"Сыворотка для лица с гиалуроновой кислотой антивозрастная","description":"Гиалуроновая кислота лицо сывороточная антивозрастная поры 15 мл Товар с Taobao. Продавец:","price":825.50}, 
 {"id":"f4421279-8723-473e-8223-fdc95169de0d","name":"100% минерал SPF 30 |","description":"Cerave 100% минерал SPF 30 | Товар с Taobao. Продавец: 999","price":9388.60}, 
 {"id":"e6dd3722-5bd9-4956-9693-ba0b37cfe759","name":"Stick Anti-UV Увлажняет предотвращение солнечных ожогов","description":"Suncreen Stick Anti-UV Увлажняет предотвращение солнечных ожогов Товар с Taobao. Продавец: 7172","price":421.20}, 
 {"id":"78f61bba-0f19-49ab-8508-248f37024943","name":"Duo/K+ очищающий пенообразующий гель-очищающее средство","description":"Effaclar Duo/K+ очищающий пенообразующий гель -очищающее средство/солнцезащитный крем/B5/ Товар с Taobao. Продавец:","price":494.00}, 
 {"id":"c9a0093f-3e3f-45ca-a20e-f704545e775e","name":"Балаклава лыжная маска утеплённая унисекс","description":"Балаклава маска маска лыжная маска для мужчин, женщины, полноценная маска, хо Товар с Taobao. Продавец: rungui","price":184.60}, 
 {"id":"20b3beb6-6731-436e-8e40-4f31b8422884","name":"Сыворотка для лица с ретинолом увлажняющая и укрепляющая","description":"Ретинол лица сывороточная увлажняющая белая укрепляющаяся тонкая тонкая Товар с Taobao. Продавец:","price":179.40}, 
 {"id":"3733cc1b-30bc-4b47-af11-2db2952355d1","name":"Крем увлажняющий Laike","description":"Кремовый кремовый кремовый кремовый кремовый кремовый крем Товар с Taobao. Продавец: MISS ROSE Official Store","price":917.80}, 
 {"id":"713be0be-61b3-4c46-860e-b85750b00110","name":"Лицо увлажняет ланолиновое масляное кремовое","description":"Лицо увлажняет ланолиновое масляное кремовое кремовое\n\nТовар с Taobao. Продавец: MISS ROSE Official Store","price":917.80}, 
 {"id":"1a20c8db-9522-4921-a8f9-43f0af20d2ed","name":"Ночная маска для лица увлажняющая, 6 шт","description":"6 шт. Маленький пудинг спящий маска Увлажняющая маска на лице\n\nТовар с Taobao. Продавец: tb424435329","price":182.00}, 
 {"id":"928ac9e4-125b-4daa-8b6d-54f09f9eb8fc","name":"Гиалуроновая кислота маска для маски отбеливания красоты","description":"Гиалуроновая кислота маска для маски для отбеливания красоты на лице\n\nТовар с Taobao. Продавец: tb424435329","price":236.60}, 
 {"id":"8426f043-0ccf-46a4-93d3-9f10b909a216","name":"Маски тканевые для лица увлажняющие набор 10 шт","description":"10 шт. Увлажняющая питательная маска Фаск\n\nТовар с Taobao. Продавец: tb424435329","price":182.00}, 
 {"id":"5caaba1f-c80c-45da-abde-fa665a7011ea","name":"Гель для очищения кожи с алоэ вера увлажняющий","description":"Очистка кожи алоэ вера очистка, увлажнение и увлажнение Товар с Taobao. Продавец:","price":223.60}, 
 {"id":"d6068e08-40bd-4e7f-8a9a-5491ad5e4f16","name":"Маска из зеленого чая очищать лицо Чистое отбеливание грязи","description":"Маска из зеленого чая очищать лицо Чистое маска отбеливание грязи Товар с Taobao. Продавец:","price":404.30}, 
 {"id":"1b855581-c5fa-49d8-9219-70e2ce234961","name":"Сажая розовая маска отбеливающая для лица","description":"Сажая розовая маска отбеливающая маска для лица\n\nТовар с Taobao. Продавец: tb424435329","price":239.20}, 
 {"id":"5f416ade-bea4-41ed-ad05-f84aad91280a","name":"Полная серия по уходу за кожей EF отправляет La Man Serum","description":"Полная серия по уходу за кожей EF отправляет La Man Serum Niacin Ami 10\n\nТовар с Taobao. Продавец: BeautyNail Art Store","price":578.50}, 
 {"id":"7080fb0d-e0c4-4376-bb38-a4b79261ea52","name":"Горячий туман увлажняющий лицевой увлажнительное лицо","description":"Горячий туман увлажняющий лицевой увлажнительное увлажнительное лицо\n\nТовар с Taobao. Продавец: YJ258 Store","price":1097.20}, 
 {"id":"d0bd42bc-1fb7-4c47-9536-8838a30f831e","name":"Арбутин лиц, отбеливающий сыворот","description":"Арбутин лиц, отбеливающий сыворот Товар с Taobao. Продавец:","price":367.90}, 
 {"id":"b403b047-9b34-422d-9262-9c946641eb50","name":"Куркума лица сывороточная органическая отбеливание против","description":"Куркума лица сывороточная органическая отбеливание против старения масла морщин\n\nТовар с Taobao. Продавец: chenqq977","price":529.10}, 
 {"id":"44aed871-669b-4eb5-90d3-ba31e66c868f","name":"Патчи для глаз с авокадо и коллагеном, 60 шт","description":"60 шт. Авокадо коллагеновая маска для глаз.\n\nТовар с Taobao. Продавец: tb424435329","price":18153.20}, 
 {"id":"3937ed22-257d-41b1-885c-6d7454d78344","name":"Отбеливающий крем для лица с коллагеном и молоком","description":"Витамин С лица отбеливание кремового крема Товар с Taobao. Продавец:","price":637.00}, 
 {"id":"845bfde6-26e6-4fae-bfb4-65ad3c0ae0d6","name":"Лосьон для тела отбеливающий увлажняющий","description":"Лосьон для отбеливания тела крем\n\nТовар с Taobao. Продавец: chenqq977","price":492.70}, 
 {"id":"a3e8dbb1-b3e3-4122-a857-7b24904025bd","name":"Система очистки кожи и комплект по уходу за телом","description":"Система очистки кожи и комплект по уходу за телом Товар с Taobao. Продавец:","price":7189.00}, 
 {"id":"3d01024d-68c4-43fe-b4b2-0da21c4f81d9","name":"Уход за кожей бамбук угля","description":"Уход за кожей бамбук угля Товар с Taobao. Продавец:","price":209.30}, 
 {"id":"19e387d9-4d88-423c-be70-d87dbf86a1eb","name":"Увлажняющая помада с осветляющим эффектом","description":"Увлажняющий осветляющий увлажнение помады и Товар с Taobao. Продавец: DM","price":366.60}, 
 {"id":"569bcd00-a6cb-4a55-bc14-b3dbf2ba5981","name":"Ночная коллагенная маска омолаживание увлажняющее бриг h","description":"Ночная коллагенная маска омолаживание увлажняющее бриг h\n\nТовар с Taobao. Продавец: Overall Makeup Store","price":380.90}, 
 {"id":"6deb10ee-678a-4696-a5a2-ef45b77c4e66","name":"Увлажняющий лосьон Cerave SPF 30 Никотинамид","description":"Увлажняющий лосьон Cerave SPF 30 Никотинамид Товар с Taobao. Продавец:","price":573.30}, 
 {"id":"0fb7de04-fdb5-421d-ac82-210edb5d402f","name":"Маска регидратационная Поры увлажняют гиалуроновую кислоту","description":"Маска регидратационная маска Поры увлажняют гиалуроновую кислоту\n\nТовар с Taobao. Продавец: MISS ROSE Official Store","price":917.80}, 
 {"id":"bd250eda-33c1-4659-9ece-572013a0dfb5","name":"Салициловая кислота лицо в сыворот","description":"Салициловая кислота лицо в сыворот Товар с Taobao. Продавец: DM","price":495.30}, 
 {"id":"385d821d-e235-4a39-be7b-105e57aa94c0","name":"Сыворотка Пятно темные пятна Куркули","description":"Сыворотка Пятно темные пятна Куркули Товар с Taobao. Продавец: healthylive","price":364.00}, 
 {"id":"b308c111-f33b-4b98-ac62-379b823e9e90","name":"Лицо сывороточного витамина витамин кретинг укрепляя кожа","description":"Лицо сывороточного витамина витамин кретинг укрепляя кожа Товар с Taobao. Продавец:","price":404.30}, 
 {"id":"0b4361e7-3a88-4c47-81b7-66bc16ca2c09","name":"Изолированная солнцезащитная палка Лето освежающее тело","description":"Suncreen Изолированная солнцезащитная палка Лето освежающее тело Товар с Taobao. Продавец: 7172","price":292.50}, 
 {"id":"9fba4591-8ca3-49f0-96e6-8ed404cace65","name":"Универсальное кружево маленькое платок","description":"Универсальное кружево маленькое платок Товар с Taobao. Продавец:","price":1406.60}, 
 {"id":"f90c7d6f-f284-4551-b80a-65468e396dae","name":"Солнцезащитный крем для лица и тела, отбеливающий кожи","description":"Солнцезащитный крем для лица и тела, отбеливающий солнцезащитный крем для кожи Товар с Taobao. Продавец: 7172","price":180.70}, 
 {"id":"2a8c4369-c079-42f0-9da3-7841346afbea","name":"Темное пятно правильное или отбеливающее сывороточное лиц","description":"Темное пятно правильное или отбеливающее сывороточное лицо, отбеливающая сыворот Товар с Taobao. Продавец:","price":477.10}, 
 {"id":"afe6c081-983b-47e0-b48a-b99141f2e3ca","name":"Оригинальная Centella Serum Увлажняющая анти-морщина","description":"Оригинальная Centella Serum Увлажняющая увлажняющая анти-морщина\n\nТовар с Taobao. Продавец: BeautyNail Art Store","price":809.90}, 
 {"id":"5183f7ed-2937-478b-851b-6960eb24c97e","name":"Night Face Cream, увлажняющий крем для сухой кожи ночной","description":"Ntoulon Night Face Cream, увлажняющий крем для сухой кожи ночной крем Товар с Taobao. Продавец:","price":6418.10}, 
 {"id":"32a31bac-5938-455f-b517-b3137673bfc2","name":"Сыворотка для лица с ниацинамидом 15% отбеливающая","description":"15% отбеливающего лица Niacin AMI Сывороточная увлажняющая антиоооооталя Товар с Taobao. Продавец: DM","price":707.20}, 
 {"id":"40c30cb0-ca66-4bea-8a43-c22d59be6a9f","name":"Зеркальное жемчужное блеск губы водонепроницаемые увлажня","description":"Зеркальное жемчужное блеск губы водонепроницаемые увлажняющие Товар с Taobao. Продавец:","price":184.60}, 
 {"id":"43168868-3503-43b5-9296-c87f138d402d","name":"Лосьон для тела глубокий увлажняющий крем от отбеливания","description":"Качественный товар из категории Здоровье и красота","price":1101.10}, 
 {"id":"4b4f8d99-039c-434b-b2d1-1a53414a9206","name":"Солнцезащитный костюм для мужской, легкой куртки на откры","description":"Солнцезащитный костюм для мужской, легкой куртки на открытом воздухе\n\nТовар с Taobao. Продавец: vkkpu Discount Shop","price":712.40}, 
 {"id":"5de0aa71-514a-4cb8-b8f6-c53b2300ad33","name":"Поры лактобионовой кислоты сжимают сыворотку гиалуроновую","description":"Поры лактобионовой кислоты сжимают сыворотку гиалуроновую кислоту MOIS Товар с Taobao. Продавец:","price":422.50}, 
 {"id":"c690a9ad-a7ca-4954-aa65-d444a2b1f865","name":"Солнцезащитный крем SPF 50+ Face Oncreen Без масляной уль","description":"Солнцезащитный крем SPF 50+ Face Oncreen Без масляной ультра-световой жидкости Товар с Taobao. Продавец:","price":343.20}, 
 {"id":"4e6ff28c-02f3-45d0-a329-5db7baad3ce7","name":"Телефонный кабельный трекер проволоки rj тонер Tra","description":"Masstech Телефонный кабельный кабельный кабельный трекер проволоки rj тонер Tra Товар с Taobao. Продавец: LCY70","price":2843.10}, 
 {"id":"55e67dd9-b198-424a-8159-87a1e3a819ba","name":"Электрическая щётка для чистки с насадками","description":"Электрическое очищающее средство для очистки по уходу за лицом по уходу за лицом по уходу за лицом Товар с Taobao. Продавец:","price":1320.80}, 
 {"id":"59515ffa-5de1-45d2-a6d4-e8922515f073","name":"Патчи гидрогелевые для глаз с золотом и авокадо","description":"Гидрогелевые патчи для кожи вокруг глаз с коллоидным золотом и маслом авокадо. Интенсивно увлажняют, разглаживают мелкие морщинки, уменьшают тёмные круги и отёчность. Охлаждающий эффект снимает усталость глаз.\n\n• Количество: 60 шт (30 пар)\n• Активные компоненты: золото, авокадо, гиалуроновая кислота\n• Действие: увлажнение, лифтинг, осветление\n• Время воздействия: 15-20 минут\n• Подходит для всех типов кожи","price":33885.80}, 
 {"id":"d7ae1387-2c0e-4d43-88cc-e791e4faaebf","name":"Крем крема для лица витамина С Удалить темные пятна отбел","description":"Крем крема для лица витамина С Удалить темные пятна отбеливание Товар с Taobao. Продавец:","price":422.50}, 
 {"id":"e100577d-3a1f-4bc8-87d8-c3bf5e1e62be","name":"Арбуз ниацинамид лицо сыворотка новая светящаяся лице","description":"Арбуз ниацинамид лицо сыворотка новая светящаяся лице Товар с Taobao. Продавец: healthylive","price":386.10}, 
 {"id":"ed06fb58-170a-4e2c-93b3-e3ee09c45c7e","name":"Тонер для лица с ниацинамидом отбеливающий увлажняющий","description":"Лицо ниацинамид тонер отбеливание сыворотки Увлажняющее увлажнение Товар с Taobao. Продавец: healthylive","price":806.00}, 
 {"id":"7986836c-124a-42ba-9fdf-531ea09aba46","name":"Никотинамид арбутин отбеливающий увлажняющий уход за коже","description":"Никотинамид арбутин отбеливающий увлажняющий уход за кожей PR Товар с Taobao. Продавец:","price":219.70}, 
 {"id":"71d92723-bb12-48ec-bdd0-5167f4dadd9e","name":"Солнцезащитный крем с витамином С увлажняющим минералом","description":"Солнцезащитный крем с витамином С с увлажняющим минералом SPF 40 Товар с Taobao. Продавец:","price":404.30}]